{
  "$schema": "https://mintlify.com/docs.json",
  "name": "HealthIA",
  "theme": "almond",
  "colors": {
    "primary": "#2E86AB",
    "light": "#E8F4F8",
    "dark": "#1A5276"
  },
  "navbar": {
    "primary": {
      "type": "github",
      "href": "https://github.com/Rafael-Lee1/healthia-diagnostico-inteligente"
    }
  },
  "footer": {
    "socials": {
      "github": "https://github.com/Rafael-Lee1/healthia-diagnostico-inteligente"
    }
  },
  "navigation": {
    "tabs": [
      {
        "tab": "Documentation",
        "groups": [
          {
            "group": "Get Started",
            "pages": ["introduction", "quickstart"]
          },
          {
            "group": "Core Features",
            "pages": [
              "features/symptom-analysis",
              "features/patient-context",
              "features/differential-suggestions",
              "features/explainability",
              "features/history"
            ]
          },
          {
            "group": "Architecture",
            "pages": [
              "architecture/overview",
              "architecture/backend",
              "architecture/frontend",
              "architecture/ml-pipeline"
            ]
          },
          {
            "group": "Local Development",
            "pages": [
              "development/setup",
              "development/backend",
              "development/frontend",
              "development/training"
            ]
          },
          {
            "group": "Safety & Privacy",
            "pages": [
              "safety/disclaimer",
              "safety/privacy"
            ]
          }
        ]
      },
      {
        "tab": "API Reference",
        "groups": [
          {
            "group": "Overview",
            "pages": ["api/overview"]
          },
          {
            "group": "Endpoints",
            "pages": [
              "api/predict-get",
              "api/predict-post"
            ]
          },
          {
            "group": "Data Models",
            "pages": [
              "api/patient-context",
              "api/prediction-result"
            ]
          }
        ]
      }
    ]
  }
}
